dotfile_manager/__init__.py
dotfile_manager/__main__.py
dotfile_manager/cli.py
dotfile_manager/config.py
dotfile_manager/dotfile_manager.py
dotfile_manager/project.py
dotfile_manager/py.typed
dotfile_manager/repo.py
dotfile_manager/version.py
dotfile_manager-0.5.0.dist-info/METADATA
dotfile_manager-0.5.0.dist-info/WHEEL
dotfile_manager-0.5.0.dist-info/entry_points.txt
dotfile_manager-0.5.0.dist-info/top_level.txt
dotfile_manager-0.5.0.dist-info/RECORD
