Metadata-Version: 2.4
Name: dotfile_manager
Version: 0.5.0
Summary: A tool for managing dotfiles.
Author-email: Lionel Gulich <lgulich@ethz.ch>
Project-URL: Homepage, https://github.com/lgulich/dotfile_manager
Classifier: Programming Language :: Python :: 3
Classifier: Operating System :: OS Independent
Requires-Python: >=3.10
Requires-Dist: PyYAML
Requires-Dist: typeguard
